aaz_dev/__init__.py
aaz_dev/app/__init__.py
aaz_dev/app/app.py
aaz_dev/app/main.py
aaz_dev/app/run.py
aaz_dev/app/url_converters.py
aaz_dev/cli/__init__.py
aaz_dev/cli/api/__init__.py
aaz_dev/cli/api/_cmds.py
aaz_dev/cli/api/az.py
aaz_dev/cli/api/portal.py
aaz_dev/cli/controller/__init__.py
aaz_dev/cli/controller/az_arg_group_generator.py
aaz_dev/cli/controller/az_atomic_profile_builder.py
aaz_dev/cli/controller/az_client_generator.py
aaz_dev/cli/controller/az_command_ctx.py
aaz_dev/cli/controller/az_command_generator.py
aaz_dev/cli/controller/az_module_manager.py
aaz_dev/cli/controller/az_operation_generator.py
aaz_dev/cli/controller/az_output_generator.py
aaz_dev/cli/controller/az_profile_generator.py
aaz_dev/cli/controller/az_selector_generator.py
aaz_dev/cli/controller/portal_cli_generator.py
aaz_dev/cli/model/__init__.py
aaz_dev/cli/model/atomic/__init__.py
aaz_dev/cli/model/atomic/_client.py
aaz_dev/cli/model/atomic/_command.py
aaz_dev/cli/model/atomic/_command_group.py
aaz_dev/cli/model/atomic/_example.py
aaz_dev/cli/model/atomic/_help.py
aaz_dev/cli/model/atomic/_profile.py
aaz_dev/cli/model/atomic/_resource.py
aaz_dev/cli/model/common/__init__.py
aaz_dev/cli/model/common/_fields.py
aaz_dev/cli/model/view/__init__.py
aaz_dev/cli/model/view/_command.py
aaz_dev/cli/model/view/_command_group.py
aaz_dev/cli/model/view/_module.py
aaz_dev/cli/model/view/_profile.py
aaz_dev/cli/templates/__init__.py
aaz_dev/cli/templates/_filters.py
aaz_dev/cli/templates/macros.j2
aaz_dev/cli/templates/python.j2
aaz_dev/cli/templates/aaz/__init__.py.j2
aaz_dev/cli/templates/aaz/command/_cmd.py.j2
aaz_dev/cli/templates/aaz/group/__cmd_group.py.j2
aaz_dev/cli/templates/aaz/group/__init__.py.j2
aaz_dev/cli/templates/aaz/profile/__init__.py.j2
aaz_dev/cli/templates/aaz/profile/_clients.py.j2
aaz_dev/cli/templates/extension/HISTORY.rst.j2
aaz_dev/cli/templates/extension/README.md.j2
aaz_dev/cli/templates/extension/setup.cfg.j2
aaz_dev/cli/templates/extension/setup.py.j2
aaz_dev-4.5.3.dist-info/licenses/LICENSE
aaz_dev-4.5.3.dist-info/METADATA
aaz_dev-4.5.3.dist-info/WHEEL
aaz_dev-4.5.3.dist-info/entry_points.txt
aaz_dev-4.5.3.dist-info/top_level.txt
aaz_dev-4.5.3.dist-info/RECORD
