Metadata-Version: 2.4
Name: aaz-dev
Version: 4.5.3
Summary: Microsoft Atomic Azure CLI Commands Developer Tools
Home-page: https://github.com/Azure/aaz-dev-tools
Author: Microsoft Corporation
Author-email: azpycli@microsoft.com
License: MIT
Keywords: azure
Classifier: Development Status :: 5 - Production/Stable
Classifier: Intended Audience :: Developers
Classifier: Topic :: Software Development :: Build Tools
Classifier: Environment :: Console
Classifier: License :: OSI Approved :: MIT License
Classifier: Natural Language :: English
Classifier: Programming Language :: Python :: 3.9
Classifier: Programming Language :: Python :: 3.10
Classifier: Programming Language :: Python :: 3.11
Classifier: Programming Language :: Python :: 3.12
Classifier: Programming Language :: Python :: 3.13
Requires-Python: >=3.9
License-File: LICENSE
Requires-Dist: schematics~=2.1.1
Requires-Dist: pyyaml~=6.0.2
Requires-Dist: fuzzywuzzy~=0.18.0
Requires-Dist: pluralizer~=1.2.0
Requires-Dist: lxml>=5.0.0
Requires-Dist: flask~=3.0.3
Requires-Dist: cachelib~=0.13.0
Requires-Dist: xmltodict~=0.13.0
Requires-Dist: packaging>=21.3
Requires-Dist: Jinja2~=3.1.4
Requires-Dist: MarkupSafe>=2.1.5
Requires-Dist: jsonschema~=4.23.0
Requires-Dist: click~=8.1.2
Requires-Dist: setuptools==70.0.0
Requires-Dist: python-Levenshtein
Requires-Dist: azure-mgmt-core
Requires-Dist: azdev
Dynamic: author
Dynamic: author-email
Dynamic: classifier
Dynamic: description
Dynamic: description-content-type
Dynamic: home-page
Dynamic: keywords
Dynamic: license
Dynamic: license-file
Dynamic: requires-dist
Dynamic: requires-python
Dynamic: summary
